siepic_ebeam_pdk/DFT.xml
siepic_ebeam_pdk/EBeam.lyp
siepic_ebeam_pdk/EBeam.lyt
siepic_ebeam_pdk/FDTD.xml
siepic_ebeam_pdk/MONTECARLO.xml
siepic_ebeam_pdk/Verification.xml
siepic_ebeam_pdk/WAVEGUIDES.xml
siepic_ebeam_pdk/WAVEGUIDES_SiN.xml
siepic_ebeam_pdk/__init__.py
siepic_ebeam_pdk/CML/Dream/Dream_CML_Installation.md
siepic_ebeam_pdk/CML/Dream/ebeam_dream_splitter_1x2_te1550.ice.x
siepic_ebeam_pdk/CML/Dream/ebeam_sin_dream_splitter1x2_te1550.ice
siepic_ebeam_pdk/CML/EBeam/GC_TE_1310_8degOxide_BB.ice
siepic_ebeam_pdk/CML/EBeam/GC_TE_1550_8degOxide_BB.ice
siepic_ebeam_pdk/CML/EBeam/GC_TM_1310_8degOxide_BB.ice
siepic_ebeam_pdk/CML/EBeam/GC_TM_1550_8degOxide_BB.ice
siepic_ebeam_pdk/CML/EBeam/contra_directional_coupler.ice
siepic_ebeam_pdk/CML/EBeam/contra_directional_coupler_te1310.ice
siepic_ebeam_pdk/CML/EBeam/ebeam_adiabatic_te1550.ice
siepic_ebeam_pdk/CML/EBeam/ebeam_adiabatic_tm1550.ice
siepic_ebeam_pdk/CML/EBeam/ebeam_bdc_te1550.ice
siepic_ebeam_pdk/CML/EBeam/ebeam_bragg_te1550.ice
siepic_ebeam_pdk/CML/EBeam/ebeam_crossing4.ice
siepic_ebeam_pdk/CML/EBeam/ebeam_dc_2-1_te895.ice
siepic_ebeam_pdk/CML/EBeam/ebeam_dc_halfring_straight.ice
siepic_ebeam_pdk/CML/EBeam/ebeam_dc_te1550.ice
siepic_ebeam_pdk/CML/EBeam/ebeam_dc_te895.ice
siepic_ebeam_pdk/CML/EBeam/ebeam_disconnected_te1550.ice
siepic_ebeam_pdk/CML/EBeam/ebeam_disconnected_tm1550.ice
siepic_ebeam_pdk/CML/EBeam/ebeam_gc_te1550.ice
siepic_ebeam_pdk/CML/EBeam/ebeam_gc_tm1550.ice
siepic_ebeam_pdk/CML/EBeam/ebeam_splitter_swg_assist_te1550.ice
siepic_ebeam_pdk/CML/EBeam/ebeam_taper_te1550.ice
siepic_ebeam_pdk/CML/EBeam/ebeam_terminator_te1310.ice
siepic_ebeam_pdk/CML/EBeam/ebeam_terminator_te1550.ice
siepic_ebeam_pdk/CML/EBeam/ebeam_terminator_te895.ice
siepic_ebeam_pdk/CML/EBeam/ebeam_terminator_tm1550.ice
siepic_ebeam_pdk/CML/EBeam/ebeam_wg_integral_1310.ice
siepic_ebeam_pdk/CML/EBeam/ebeam_wg_integral_1550.ice
siepic_ebeam_pdk/CML/EBeam/ebeam_wg_integral_895.ice
siepic_ebeam_pdk-0.4.53.dist-info/METADATA
siepic_ebeam_pdk-0.4.53.dist-info/WHEEL
siepic_ebeam_pdk-0.4.53.dist-info/top_level.txt
siepic_ebeam_pdk-0.4.53.dist-info/RECORD
