Metadata-Version: 2.4
Name: siepic_ebeam_pdk
Version: 0.4.53
Summary: SiEPIC_EBeam_PDK: process design kit (PDK) for fabrication using electron beam lithography, and a library silicon photonics components. 
Author-email: Lukas Chrostowski <lukasc@ece.ubc.ca>
Project-URL: Homepage, https://github.com/SiEPIC/SiEPIC_EBeam_PDK
Project-URL: Issues, https://github.com/SiEPIC/SiEPIC_EBeam_PDK/issues
Classifier: Programming Language :: Python :: 3
Classifier: License :: OSI Approved :: MIT License
Classifier: Operating System :: OS Independent
Requires-Python: >=3.8
Requires-Dist: SiEPIC>=0.5.20
Requires-Dist: numpy
Requires-Dist: packaging
